py_lexorank/__init__.py
py_lexorank/lexorank_key.py
py_lexorank/lexorank/__init__.py
py_lexorank/lexorank/lexo_decimal.py
py_lexorank/lexorank/lexo_integer.py
py_lexorank/lexorank/lexo_rank.py
py_lexorank/lexorank/lexo_rank_bucket.py
py_lexorank/lexorank/numeral_systems.py
py_lexorank-1.0.2.dist-info/licenses/LICENSE
py_lexorank-1.0.2.dist-info/METADATA
py_lexorank-1.0.2.dist-info/WHEEL
py_lexorank-1.0.2.dist-info/top_level.txt
py_lexorank-1.0.2.dist-info/RECORD
