Metadata-Version: 2.4
Name: py-lexorank
Version: 1.0.2
Summary: Lightweight, dependency-free Python implementation of LexoRank algorithm for fractional indexing
Author-email: ixfcao <2717176337@qq.com>
License: MIT License
Project-URL: Homepage, https://github.com/ixfcao/lexorank-py
Project-URL: Repository, https://github.com/ixfcao/lexorank-py
Project-URL: Documentation, https://github.com/ixfcao/lexorank-py#readme
Keywords: lexorank,sorting,indexing,database,ordering,fractional-indexing,rebalancing
Classifier: Development Status :: 4 - Beta
Classifier: Intended Audience :: Developers
Classifier: Programming Language :: Python :: 3
Classifier: Programming Language :: Python :: 3.10
Classifier: Programming Language :: Python :: 3.11
Classifier: Programming Language :: Python :: 3.12
Classifier: Programming Language :: Python :: 3.13
Requires-Python: >=3.10
License-File: LICENSE
Provides-Extra: dev
Requires-Dist: pytest>=6.0; extra == "dev"
Requires-Dist: pytest-cov; extra == "dev"
Requires-Dist: black; extra == "dev"
Requires-Dist: flake8; extra == "dev"
Dynamic: license-file
